energyplus_version/__about__.py
energyplus_version/__init__.py
energyplus_version/__main__.py
energyplus_version/schema.py
energyplus_version/upgrade.py
energyplus_version/version_23_2_0.py
energyplus_version/versioning.py
energyplus_version/cli/__init__.py
energyplus_version-1.0.0.dist-info/METADATA
energyplus_version-1.0.0.dist-info/WHEEL
energyplus_version-1.0.0.dist-info/entry_points.txt
energyplus_version-1.0.0.dist-info/licenses/LICENSE.txt
energyplus_version-1.0.0.dist-info/RECORD
