Metadata-Version: 2.3
Name: energyplus-version
Version: 1.0.0
Summary: Change the version of an EnergyPlus epJSON file
Project-URL: Documentation, https://github.com/building-physics/energyplus_version#readme
Project-URL: Issues, https://github.com/building-physics/energyplus_version/issues
Project-URL: Source, https://github.com/building-physics/energyplus_version
Author: Jason W. DeGraw, Niraj Kunwar
Maintainer-email: "Jason W. DeGraw" <jason.degraw@gmail.com>
License-Expression: BSD-3-Clause
License-File: LICENSE.txt
Classifier: Development Status :: 4 - Beta
Classifier: Programming Language :: Python
Classifier: Programming Language :: Python :: 3.8
Classifier: Programming Language :: Python :: 3.9
Classifier: Programming Language :: Python :: 3.10
Classifier: Programming Language :: Python :: 3.11
Classifier: Programming Language :: Python :: 3.12
Classifier: Programming Language :: Python :: Implementation :: CPython
Classifier: Programming Language :: Python :: Implementation :: PyPy
Requires-Python: >=3.8
Requires-Dist: click
Requires-Dist: jsonpatch
Requires-Dist: jsonschema
